g2v/app.py
g2v/cli.py
g2v/config.py
g2v/data_processing.py
g2v/plotting.py
g2v/roi_manager.py
g2v/utils.py
g2v-0.1.2.dist-info/licenses/LICENSE
g2v-0.1.2.dist-info/METADATA
g2v-0.1.2.dist-info/WHEEL
g2v-0.1.2.dist-info/entry_points.txt
g2v-0.1.2.dist-info/top_level.txt
g2v-0.1.2.dist-info/RECORD
