Metadata-Version: 2.4
Name: g2v
Version: 0.1.2
Summary: Viewing XPCS g2 curves in a web interface.
Author-email: Damian Guenzing <dguenzing@lbl.gov>
Maintainer-email: Damian Guenzing <dguenzing@lbl.gov>
License-Expression: MIT
Project-URL: bugs, https://github.com/gnzng/g2v/issues
Project-URL: changelog, https://github.com/gnzng/g2v/blob/master/changelog.md
Project-URL: homepage, https://github.com/gnzng/g2v
Classifier: Programming Language :: Python :: 3
Classifier: Operating System :: OS Independent
License-File: LICENSE
Requires-Dist: numpy
Requires-Dist: pandas
Requires-Dist: h5py
Requires-Dist: streamlit
Requires-Dist: plotly
Requires-Dist: loguru
Requires-Dist: pyzmq
Provides-Extra: docs
Requires-Dist: sphinx; extra == "docs"
Requires-Dist: sphinx-rtd-theme; extra == "docs"
Provides-Extra: test
Requires-Dist: pytest>=7.0; extra == "test"
Requires-Dist: pytest-cov; extra == "test"
Requires-Dist: pytest-mock; extra == "test"
Requires-Dist: pytest-asyncio; extra == "test"
Dynamic: license-file
